{
    "_links": {
        "self": {
            "href": "http:\/\/default\/media\/8?_format=hal_json"
        },
        "type": {
            "href": "http:\/\/drupal.org\/rest\/type\/media\/image"
        },
        "http:\/\/drupal.org\/rest\/relation\/media\/image\/thumbnail": [
            {
                "href": "http:\/\/default\/sites\/default\/files\/2017-04\/nature-background-images2.jpg"
            }
        ],
        "http:\/\/drupal.org\/rest\/relation\/media\/image\/uid": [
            {
                "href": "http:\/\/default\/user\/1?_format=hal_json"
            }
        ],
        "http:\/\/drupal.org\/rest\/relation\/media\/image\/revision_uid": [
            {
                "href": "http:\/\/default\/user\/1?_format=hal_json"
            }
        ],
        "http:\/\/drupal.org\/rest\/relation\/media\/image\/field_image": [
            {
                "href": "http:\/\/default\/sites\/default\/files\/2017-04\/nature-background-images2.jpg"
            }
        ]
    },
    "mid": [
        {
            "value": 8
        }
    ],
    "uuid": [
        {
            "value": "52008027-9d69-4069-a39d-80f0a885ed9d"
        }
    ],
    "vid": [
        {
            "value": 8
        }
    ],
    "bundle": [
        {
            "target_id": "image"
        }
    ],
    "langcode": [
        {
            "value": "en",
            "lang": "en"
        }
    ],
    "name": [
        {
            "value": "Tree"
        }
    ],
    "_embedded": {
        "http:\/\/drupal.org\/rest\/relation\/media\/image\/thumbnail": [
            {
                "_links": {
                    "self": {
                        "href": "http:\/\/default\/sites\/default\/files\/2017-04\/nature-background-images2.jpg"
                    },
                    "type": {
                        "href": "http:\/\/drupal.org\/rest\/type\/file\/file"
                    }
                },
                "uuid": [
                    {
                        "value": "51b8e49e-b7c9-42e5-9b12-ef0811efffe0"
                    }
                ],
                "uri": [
                    {
                        "value": "http:\/\/default\/sites\/default\/files\/2017-04\/nature-background-images2.jpg"
                    }
                ]
            }
        ],
        "http:\/\/drupal.org\/rest\/relation\/media\/image\/uid": [
            {
                "_links": {
                    "self": {
                        "href": "http:\/\/default\/user\/1?_format=hal_json"
                    },
                    "type": {
                        "href": "http:\/\/drupal.org\/rest\/type\/user\/user"
                    }
                },
                "uuid": [
                    {
                        "value": "b89eed65-c66e-42a9-8c1d-3512c8605f41"
                    }
                ]
            }
        ],
        "http:\/\/drupal.org\/rest\/relation\/media\/image\/revision_uid": [
            {
                "_links": {
                    "self": {
                        "href": "http:\/\/default\/user\/1?_format=hal_json"
                    },
                    "type": {
                        "href": "http:\/\/drupal.org\/rest\/type\/user\/user"
                    }
                },
                "uuid": [
                    {
                        "value": "b89eed65-c66e-42a9-8c1d-3512c8605f41"
                    }
                ]
            }
        ],
        "http:\/\/drupal.org\/rest\/relation\/media\/image\/field_image": [
            {
                "_links": {
                    "self": {
                        "href": "http:\/\/default\/sites\/default\/files\/2017-04\/nature-background-images2.jpg"
                    },
                    "type": {
                        "href": "http:\/\/drupal.org\/rest\/type\/file\/file"
                    }
                },
                "uuid": [
                    {
                        "value": "51b8e49e-b7c9-42e5-9b12-ef0811efffe0"
                    }
                ],
                "uri": [
                    {
                        "value": "http:\/\/default\/sites\/default\/files\/2017-04\/nature-background-images2.jpg"
                    }
                ]
            }
        ]
    },
    "status": [
        {
            "value": true
        }
    ],
    "created": [
        {
            "value": 1493222415
        }
    ],
    "changed": [
        {
            "value": 1493222415
        }
    ],
    "revision_timestamp": [
        {
            "value": 1493222415
        }
    ],
    "default_langcode": [
        {
            "value": true,
            "lang": "en"
        }
    ]
}